mcp_atlassian/__init__.py
mcp_atlassian/exceptions.py
mcp_atlassian/confluence/__init__.py
mcp_atlassian/confluence/client.py
mcp_atlassian/confluence/comments.py
mcp_atlassian/confluence/config.py
mcp_atlassian/confluence/constants.py
mcp_atlassian/confluence/labels.py
mcp_atlassian/confluence/pages.py
mcp_atlassian/confluence/search.py
mcp_atlassian/confluence/spaces.py
mcp_atlassian/confluence/users.py
mcp_atlassian/confluence/utils.py
mcp_atlassian/confluence/v2_adapter.py
mcp_atlassian/jira/__init__.py
mcp_atlassian/jira/attachments.py
mcp_atlassian/jira/boards.py
mcp_atlassian/jira/client.py
mcp_atlassian/jira/comments.py
mcp_atlassian/jira/config.py
mcp_atlassian/jira/constants.py
mcp_atlassian/jira/epics.py
mcp_atlassian/jira/fields.py
mcp_atlassian/jira/formatting.py
mcp_atlassian/jira/issues.py
mcp_atlassian/jira/links.py
mcp_atlassian/jira/projects.py
mcp_atlassian/jira/protocols.py
mcp_atlassian/jira/search.py
mcp_atlassian/jira/sprints.py
mcp_atlassian/jira/transitions.py
mcp_atlassian/jira/users.py
mcp_atlassian/jira/worklog.py
mcp_atlassian/models/__init__.py
mcp_atlassian/models/base.py
mcp_atlassian/models/constants.py
mcp_atlassian/models/confluence/__init__.py
mcp_atlassian/models/confluence/comment.py
mcp_atlassian/models/confluence/common.py
mcp_atlassian/models/confluence/label.py
mcp_atlassian/models/confluence/page.py
mcp_atlassian/models/confluence/search.py
mcp_atlassian/models/confluence/space.py
mcp_atlassian/models/confluence/user_search.py
mcp_atlassian/models/jira/__init__.py
mcp_atlassian/models/jira/agile.py
mcp_atlassian/models/jira/comment.py
mcp_atlassian/models/jira/common.py
mcp_atlassian/models/jira/issue.py
mcp_atlassian/models/jira/link.py
mcp_atlassian/models/jira/project.py
mcp_atlassian/models/jira/search.py
mcp_atlassian/models/jira/version.py
mcp_atlassian/models/jira/workflow.py
mcp_atlassian/models/jira/worklog.py
mcp_atlassian/preprocessing/__init__.py
mcp_atlassian/preprocessing/base.py
mcp_atlassian_bruno-0.1.27.dist-info/METADATA
mcp_atlassian_bruno-0.1.27.dist-info/WHEEL
mcp_atlassian_bruno-0.1.27.dist-info/entry_points.txt
mcp_atlassian_bruno-0.1.27.dist-info/licenses/LICENSE
mcp_atlassian_bruno-0.1.27.dist-info/RECORD
